LICENSE
MANIFEST.in
README.rst
setup.py
guniflask_cli/__init__.py
guniflask_cli/config.py
guniflask_cli/errors.py
guniflask_cli/gunicorn.py
guniflask_cli/main.py
guniflask_cli/sqlgen.py
guniflask_cli/utils.py
guniflask_cli.egg-info/PKG-INFO
guniflask_cli.egg-info/SOURCES.txt
guniflask_cli.egg-info/dependency_links.txt
guniflask_cli.egg-info/entry_points.txt
guniflask_cli.egg-info/not-zip-safe
guniflask_cli.egg-info/requires.txt
guniflask_cli.egg-info/top_level.txt
guniflask_cli/commands/__init__.py
guniflask_cli/commands/build.py
guniflask_cli/commands/debug.py
guniflask_cli/commands/init.py
guniflask_cli/commands/restart.py
guniflask_cli/commands/start.py
guniflask_cli/commands/stop.py
guniflask_cli/commands/table2model.py
guniflask_cli/commands/version.py
guniflask_cli/templates/project/.dockerignore
guniflask_cli/templates/project/.gitignore
guniflask_cli/templates/project/Dockerfile.jinja2
guniflask_cli/templates/project/_project_name/__init__.py.jinja2
guniflask_cli/templates/project/_project_name/app.py
guniflask_cli/templates/project/_project_name/config/__init__.py
guniflask_cli/templates/project/_project_name/config/jwt_config.py
guniflask_cli/templates/project/_project_name/config/security_config.py.jinja2
guniflask_cli/templates/project/bin/manage
guniflask_cli/templates/project/conf/_project_name.py.jinja2
guniflask_cli/templates/project/conf/gunicorn.py.jinja2
guniflask_cli/templates/project/requirements/app.txt.jinja2
guniflask_cli/templates/project/requirements/test.txt
guniflask_cli/templates/project/tests/__init__.py
guniflask_cli/templates/project/tests/conftest.py
requirements/test.txt
tests/__init__.py
tests/test_init_project.py